aeskeyschedule/__init__.py
aeskeyschedule/aeskeyschedule.py
aeskeyschedule/main.py
aeskeyschedule-0.0.3.dist-info/LICENSE
aeskeyschedule-0.0.3.dist-info/METADATA
aeskeyschedule-0.0.3.dist-info/WHEEL
aeskeyschedule-0.0.3.dist-info/entry_points.txt
aeskeyschedule-0.0.3.dist-info/top_level.txt
aeskeyschedule-0.0.3.dist-info/RECORD
