Metadata-Version: 2.1
Name: aeskeyschedule
Version: 0.0.3
Summary: Tool to calculate the Rijndael key schedule given any AES-128 round key.
Home-page: https://github.com/fanosta/aeskeyschedule
Author: fanosta
Author-email: fanosta@users.noreply.github.com
License: UNKNOWN
Platform: UNKNOWN
Classifier: Programming Language :: Python :: 3
Classifier: License :: OSI Approved :: MIT License
Classifier: Operating System :: OS Independent
Requires-Dist: colorama (>=0.4.1)
